common/__init__.py
common/logging_utils.py
common/openapi.py
common/utils.py
docgraph/__init__.py
docgraph/__main__.py
docgraph/build.yaml
docgraph/jsonutil.py
docgraph/version.py
docgraph-0.0.14.dev0.dist-info/LICENSE
docgraph-0.0.14.dev0.dist-info/METADATA
docgraph-0.0.14.dev0.dist-info/WHEEL
docgraph-0.0.14.dev0.dist-info/top_level.txt
docgraph-0.0.14.dev0.dist-info/RECORD
