Metadata-Version: 2.1
Name: docgraph
Version: 0.0.14.dev0
Summary: Document Graph for LLM retrieval augmented genration embedding search and Completion context
Home-page: https://github.com/brad-larson-tfs/docgraph
Author: Brad Larson
Author-email: <brad.larson1@thermofisher.com>
License: UNKNOWN
Keywords: python,Machine Learning,LLM,Generative AI,Retrieval Augmented Generaiton,RAG,Embeddings,Completions,Document Graph
Platform: UNKNOWN
Classifier: Development Status :: 4 - Beta
Classifier: Intended Audience :: Developers
Classifier: License :: OSI Approved :: Apache Software License
Classifier: Programming Language :: Python :: 3
Classifier: Operating System :: POSIX :: Linux
Requires-Dist: pymupdf
Requires-Dist: pyyaml
Requires-Dist: tiktoken
Requires-Dist: tqdm
